sgx_ias_structs-0.2.0.dist-info/METADATA
sgx_ias_structs-0.2.0.dist-info/WHEEL
sgx_ias_structs/__init__.py
sgx_ias_structs/sgx_ias_structs.cp39-win_amd64.pyd
sgx_ias_structs-0.2.0.dist-info/RECORD
