Metadata-Version: 2.4
Name: sgx-ias-structs
Version: 0.2.0
Summary: SGX structures parsing wrapper library for the Decentriq platform.
Author: "decentriq" <opensource@decentriq.ch>
Author-email: "decentriq" <opensource@decentriq.ch>
Maintainer-email: decentriq <opensource@decentriq.ch>
License: LicenseRef-DECENTRIQ-Proprietary
Requires-Python: >=3.6
